MANIFEST.in
README.rst
requirements.txt
setup.cfg
setup.py
django_msp_sms/__init__.py
django_msp_sms/__init__.pyc
django_msp_sms/autocomplete_light_registry.py
django_msp_sms/autocomplete_light_registry.pyc
django_msp_sms/config.py
django_msp_sms/config.pyc
django_msp_sms/core.py
django_msp_sms/core.pyc
django_msp_sms/forms.py
django_msp_sms/forms.pyc
django_msp_sms/models.py
django_msp_sms/models.pyc
django_msp_sms/tasks.py
django_msp_sms/tasks.pyc
django_msp_sms/tests.py
django_msp_sms/urls.py
django_msp_sms/urls.pyc
django_msp_sms/views.py
django_msp_sms/views.pyc
django_msp_sms.egg-info/PKG-INFO
django_msp_sms.egg-info/SOURCES.txt
django_msp_sms.egg-info/dependency_links.txt
django_msp_sms.egg-info/requires.txt
django_msp_sms.egg-info/top_level.txt
django_msp_sms/__pycache__/__init__.cpython-38.pyc
django_msp_sms/__pycache__/autocomplete_light_registry.cpython-38.pyc
django_msp_sms/__pycache__/config.cpython-38.pyc
django_msp_sms/__pycache__/core.cpython-38.pyc
django_msp_sms/__pycache__/forms.cpython-38.pyc
django_msp_sms/__pycache__/models.cpython-38.pyc
django_msp_sms/__pycache__/tasks.cpython-38.pyc
django_msp_sms/__pycache__/urls.cpython-38.pyc
django_msp_sms/__pycache__/views.cpython-38.pyc
django_msp_sms/modulos/__init__.py
django_msp_sms/modulos/__init__.pyc
django_msp_sms/modulos/__pycache__/__init__.cpython-38.pyc
django_msp_sms/modulos/clientes/__init__.py
django_msp_sms/modulos/clientes/__init__.pyc
django_msp_sms/modulos/clientes/forms.py
django_msp_sms/modulos/clientes/forms.pyc
django_msp_sms/modulos/clientes/models.py
django_msp_sms/modulos/clientes/models.pyc
django_msp_sms/modulos/clientes/urls.py
django_msp_sms/modulos/clientes/urls.pyc
django_msp_sms/modulos/clientes/views.py
django_msp_sms/modulos/clientes/views.pyc
django_msp_sms/modulos/clientes/__pycache__/__init__.cpython-38.pyc
django_msp_sms/modulos/clientes/__pycache__/forms.cpython-38.pyc
django_msp_sms/modulos/clientes/__pycache__/models.cpython-38.pyc
django_msp_sms/modulos/clientes/__pycache__/urls.cpython-38.pyc
django_msp_sms/modulos/clientes/__pycache__/views.cpython-38.pyc
django_msp_sms/modulos/personalizados/__init__.py
